xperibot/__init__.py
xperibot/utils.py
xperibot/xperibot.py
XperiBot-0.1.2.dist-info/LICENSE
XperiBot-0.1.2.dist-info/METADATA
XperiBot-0.1.2.dist-info/WHEEL
XperiBot-0.1.2.dist-info/top_level.txt
XperiBot-0.1.2.dist-info/RECORD
