Metadata-Version: 2.1
Name: XperiBot
Version: 0.1.2
Summary: Telegram Bot for monitoring ML experiments
Home-page: https://github.com/Skalextric/XperiBot
Author: Marco Formoso
License: UNKNOWN
Platform: UNKNOWN
Classifier: Programming Language :: Python :: 3
Classifier: License :: OSI Approved :: GNU General Public License v3 or later (GPLv3+)
Classifier: Operating System :: OS Independent
Requires-Python: >=3.6
License-File: LICENSE
Requires-Dist: numpy
Requires-Dist: matplotlib
Requires-Dist: python-telegram-bot
